tsflex/__init__.py
tsflex/chunking/__init__.py
tsflex/chunking/chunking.py
tsflex/features/__init__.py
tsflex/features/feature.py
tsflex/features/feature_collection.py
tsflex/features/function_wrapper.py
tsflex/features/integrations.py
tsflex/features/logger.py
tsflex/features/segmenter/__init__.py
tsflex/features/segmenter/strided_rolling.py
tsflex/features/segmenter/strided_rolling_factory.py
tsflex/features/utils.py
tsflex/processing/__init__.py
tsflex/processing/logger.py
tsflex/processing/series_pipeline.py
tsflex/processing/series_processor.py
tsflex/processing/utils.py
tsflex/utils/__init__.py
tsflex/utils/argument_parsing.py
tsflex/utils/attribute_parsing.py
tsflex/utils/classes.py
tsflex/utils/data.py
tsflex/utils/logging.py
tsflex-0.4.1.dist-info/LICENSE
tsflex-0.4.1.dist-info/METADATA
tsflex-0.4.1.dist-info/WHEEL
tsflex-0.4.1.dist-info/RECORD
