Metadata-Version: 2.1
Name: tsflex
Version: 0.4.1
Summary: Toolkit for flexible processing & feature extraction on time-series data
Home-page: https://github.com/predict-idlab/tsflex
License: MIT
Keywords: time-series,processing,feature-extraction,data-science,machine learning
Author: Jonas Van Der Donckt, Jeroen Van Der Donckt, Emiel Deprost
Requires-Python: >=3.8,<3.13
Classifier: License :: OSI Approved :: MIT License
Classifier: Programming Language :: Python :: 3
Classifier: Programming Language :: Python :: 3.8
Classifier: Programming Language :: Python :: 3.9
Classifier: Programming Language :: Python :: 3.10
Classifier: Programming Language :: Python :: 3.11
Classifier: Programming Language :: Python :: 3.12
Requires-Dist: dill (>=0.3.4,<0.4.0) ; python_version < "3.8"
Requires-Dist: dill (>=0.3.8,<0.4.0) ; python_version >= "3.8"
Requires-Dist: multiprocess (>=0.70.12,<0.71.0) ; python_version < "3.8"
Requires-Dist: multiprocess (>=0.70.16,<0.71.0) ; python_version >= "3.8"
Requires-Dist: numpy (>=1.22) ; python_version >= "3.8" and python_version < "3.11"
Requires-Dist: numpy (>=1.24) ; python_version >= "3.11"
Requires-Dist: pandas (>=1) ; python_version < "3.12"
Requires-Dist: pandas (>=2) ; python_version >= "3.12"
Requires-Dist: tqdm (>=4.62.3,<5.0.0)
Project-URL: Documentation, https://predict-idlab.github.io/tsflex
Project-URL: Repository, https://github.com/predict-idlab/tsflex
